gsdk/__init__.py
gsdk/core.py
gsdk/live.py
gsdk/media.py
gsdk/models.py
gsdk/storage.py
gsdk-1.1.0.dist-info/licenses/LICENSE
gsdk-1.1.0.dist-info/METADATA
gsdk-1.1.0.dist-info/WHEEL
gsdk-1.1.0.dist-info/top_level.txt
gsdk-1.1.0.dist-info/RECORD
