Metadata-Version: 2.4
Name: gsdk
Version: 1.1.0
Summary: Lightweight, high-performance Python wrapper for the Google Gemini API.
Author-email: ProgVM <progvminc@gmail.com>
License: MIT
Project-URL: Homepage, https://github.com/ProgVM/gsdk
Project-URL: Repository, https://github.com/ProgVM/gsdk.git
Project-URL: Issues, https://github.com/ProgVM/gsdk/issues
Classifier: Programming Language :: Python :: 3
Classifier: License :: OSI Approved :: MIT License
Classifier: Development Status :: 5 - Production/Stable
Classifier: Intended Audience :: Developers
Requires-Python: >=3.10
License-File: LICENSE
Requires-Dist: google-genai>=0.6.0
Requires-Dist: redis>=5.0.0
Dynamic: license-file
